zwave_ws/__init__.py
zwave_ws/WebsocketListener.py
zwave_ws/ZWaveMe.py
zwave_ws-0.1.15.dist-info/WHEEL
zwave_ws-0.1.15.dist-info/METADATA
zwave_ws-0.1.15.dist-info/RECORD
