Metadata-Version: 2.1
Name: zwave-ws
Version: 0.1.15
Summary: Library, implementing websocket connection to ZWave-Me
License: MIT
Author: Dmitry Vlasov
Author-email: kerbalspacema@gmail.com
Requires-Python: >=3.8,<4.0
Classifier: License :: OSI Approved :: MIT License
Classifier: Programming Language :: Python :: 3
Classifier: Programming Language :: Python :: 3.10
Classifier: Programming Language :: Python :: 3.8
Classifier: Programming Language :: Python :: 3.9
Requires-Dist: websocket-client (>=1.2.1,<2.0.0)
